docs/conf.py
docs/__init__.py
wiki/admin.py
wiki/apps.py
wiki/decorators.py
wiki/forms.py
wiki/managers.py
wiki/urls.py
wiki/__init__.py
wiki/conf/settings.py
wiki/conf/__init__.py
wiki/core/compat.py
wiki/core/diff.py
wiki/core/exceptions.py
wiki/core/http.py
wiki/core/permissions.py
wiki/core/utils.py
wiki/core/__init__.py
wiki/core/markdown/__init__.py
wiki/core/markdown/mdx/previewlinks.py
wiki/core/markdown/mdx/__init__.py
wiki/core/plugins/base.py
wiki/core/plugins/loader.py
wiki/core/plugins/registry.py
wiki/core/plugins/__init__.py
wiki/editors/base.py
wiki/editors/markitup.py
wiki/editors/__init__.py
wiki/locale/da/LC_MESSAGES/django.mo
wiki/locale/da/LC_MESSAGES/django.po
wiki/locale/de/LC_MESSAGES/django.mo
wiki/locale/de/LC_MESSAGES/django.po
wiki/locale/es/LC_MESSAGES/django.po
wiki/locale/fi/LC_MESSAGES/django.mo
wiki/locale/fi/LC_MESSAGES/django.po
wiki/locale/fr/LC_MESSAGES/django.mo
wiki/locale/fr/LC_MESSAGES/django.po
wiki/locale/pt_BR/LC_MESSAGES/django.mo
wiki/locale/pt_BR/LC_MESSAGES/django.po
wiki/locale/ru/LC_MESSAGES/django.mo
wiki/locale/ru/LC_MESSAGES/django.po
wiki/locale/zh_CN/LC_MESSAGES/django.mo
wiki/locale/zh_CN/LC_MESSAGES/django.po
wiki/management/__init__.py
wiki/management/commands/wikiviz.py
wiki/management/commands/__init__.py
wiki/migrations/0001_initial.py
wiki/migrations/__init__.py
wiki/models/article.py
wiki/models/pluginbase.py
wiki/models/urlpath.py
wiki/models/__init__.py
wiki/plugins/__init__.py
wiki/plugins/attachments/admin.py
wiki/plugins/attachments/forms.py
wiki/plugins/attachments/markdown_extensions.py
wiki/plugins/attachments/models.py
wiki/plugins/attachments/settings.py
wiki/plugins/attachments/urls.py
wiki/plugins/attachments/views.py
wiki/plugins/attachments/wiki_plugin.py
wiki/plugins/attachments/__init__.py
wiki/plugins/attachments/migrations/0001_initial.py
wiki/plugins/attachments/migrations/__init__.py
wiki_cb-0.14.0.1.dist-info/DESCRIPTION.rst
wiki_cb-0.14.0.1.dist-info/METADATA
wiki_cb-0.14.0.1.dist-info/metadata.json
wiki_cb-0.14.0.1.dist-info/RECORD
wiki_cb-0.14.0.1.dist-info/top_level.txt
wiki_cb-0.14.0.1.dist-info/WHEEL
