Metadata-Version: 2.0
Name: wiki-cb
Version: 0.14.0.1
Summary: Django wiki redux, maintained by Code Black
Home-page: https://github.com/audioburn/wiki-cb
Author: Code Black
Author-email: codeblack@africanawiki.org
License: GPLv3
Keywords: d,j,a,n,g,o, ,w,i,k,i, ,m,a,r,k,d,o,w,n
Platform: UNKNOWN
Classifier: Development Status :: 3 - Alpha
Classifier: License :: OSI Approved :: GNU General Public License v3 (GPLv3)
Classifier: Environment :: Web Environment
Classifier: Framework :: Django
Classifier: Intended Audience :: Developers
Classifier: Operating System :: OS Independent
Classifier: Programming Language :: Python
Classifier: Topic :: Internet :: WWW/HTTP :: Dynamic Content
Classifier: Topic :: Software Development
Classifier: Topic :: Software Development :: Libraries :: Application Frameworks
Requires-Dist: Django (>=1.4,<1.8)
Requires-Dist: django-sekizai (>=0.7)
Requires-Dist: Pillow
Requires-Dist: django-nyt (>=0.9.6)
Requires-Dist: django-mptt (==0.6.0)
Requires-Dist: six
Requires-Dist: sorl-thumbnail (>=11.12.1b)
Requires-Dist: Markdown (>2.2.0)
